pandocmath/__init__.py
pandocmath/__main__.py
pandocmath/_version.py
pandocmath/ams.py
pandocmath/filter.py
pandocmath/helper.py
pandocmath/latex_reader.py
pandocmath/pandocmath.py
pandoc_math-1.0.0.dist-info/LICENSE
pandoc_math-1.0.0.dist-info/METADATA
pandoc_math-1.0.0.dist-info/WHEEL
pandoc_math-1.0.0.dist-info/entry_points.txt
pandoc_math-1.0.0.dist-info/top_level.txt
pandoc_math-1.0.0.dist-info/RECORD
