Metadata-Version: 2.1
Name: pandoc-math
Version: 1.0.0
Summary: A pandoc filter for converting LaTeX to html for mathematics teaching
Author-email: Gavin McWhinnie <gmcwhinn@ed.ac.uk>
Project-URL: Homepage, https://github.com/GavinMcWhinnie/pandoc-math
Project-URL: Bug Tracker, https://github.com/GavinMcWhinnie/pandoc-math/issues
Classifier: Programming Language :: Python :: 3
Classifier: License :: OSI Approved :: MIT License
Classifier: Operating System :: OS Independent
Requires-Python: >=3.7
License-File: LICENSE
Requires-Dist: panflute >=2.3.0
Requires-Dist: pylatexenc >=2.10
